src/__init__.py
src/client.py
src/config_defaults.py
src/configs.py
src/abis/__init__.py
src/abis/erc20.json
src/abis/margin_account.json
src/abis/mm_entrypoint.json
src/abis/orderbook.json
src/abis/periphery.json
src/executor/orders_executor.py
src/feed/orderbook_ws.py
src/feed/rpc_ws.py
src/manager/events.py
src/manager/order.py
src/manager/orders_manager.py
src/transaction/__init__.py
src/transaction/access_list.py
src/transaction/nonce_manager.py
src/transaction/transaction.py
src/user/user.py
src/utils/__init__.py
src/utils/async_mem_cache.py
src/utils/constants.py
src/utils/errors.py
src/utils/utils.py
src/utils/validation.py
kuru_mm_py-0.1.2.dist-info/METADATA
kuru_mm_py-0.1.2.dist-info/WHEEL
kuru_mm_py-0.1.2.dist-info/top_level.txt
kuru_mm_py-0.1.2.dist-info/RECORD
