Metadata-Version: 2.4
Name: kuru-mm-py
Version: 0.1.2
Summary: Add your description here
Requires-Python: >=3.14
Requires-Dist: aiocache>=0.12.3
Requires-Dist: aiohttp>=3.9.0
Requires-Dist: asyncio>=4.0.0
Requires-Dist: loguru>=0.7.3
Requires-Dist: pytest>=9.0.2
Requires-Dist: pytest-asyncio>=1.3.0
Requires-Dist: python-dotenv>=1.0.0
Requires-Dist: web3>=7.14.0
Requires-Dist: websockets>=15.0.1
